{
  "id": "30b9a216-fea4-45ef-b478-9ad54ee94c67",
  "objective": "Crear una aplicacion de lista de tareas (todo app) con frontend React y backend FastAPI, incluyendo operaciones CRUD basicas y una interfaz de usuario moderna",
  "config": {
    "max_iterations": 50,
    "timeout_minutes": 60,
    "auto_approve": true,
    "logging_level": "INFO",
    "workspace_dir": "workspace/",
    "save_conversations": true,
    "enable_reflection": true,
    "conflict_resolution": "agent_a_priority"
  },
  "state": "failed",
  "created_at": "2025-09-27T03:31:32.431872+00:00",
  "started_at": null,
  "completed_at": null,
  "current_iteration": 0,
  "agents_status": {
    "agent_a": "AgentStatus.ERROR",
    "agent_b": "AgentStatus.ERROR"
  },
  "workspace_path": "workspace\\session_30b9a216-fea4-45ef-b478-9ad54ee94c67",
  "error_message": "Agent A (Frontend) initialization failed - check API keys and configuration"
}